fastapi_module_register/__init__.py
fastapi_module_register/base_register.py
fastapi_module_register/constants.py
fastapi_module_register/exceptions.py
fastapi_module_register/logger.py
fastapi_module_register/schema.py
fastapi_module_register/utils.py
fastapi_module_register/interface/method_interface.py
fastapi_module_register/interface/register_interface.py
fastapi_module_register/sqlmodel/__init__.py
fastapi_module_register/sqlmodel/sqlmodel_method.py
fastapi_module_register/sqlmodel/sqlmodel_reigster.py
fastapi_module_register/sqlmodel/utils.py
fastapi_module_register/tortoise/__init__.py
fastapi_module_register/tortoise/tortoise_method.py
fastapi_module_register/tortoise/tortoise_register.py
fastapi_module_register-0.0.5.dist-info/METADATA
fastapi_module_register-0.0.5.dist-info/WHEEL
fastapi_module_register-0.0.5.dist-info/licenses/LICENSE
fastapi_module_register-0.0.5.dist-info/RECORD
