Metadata-Version: 2.1
Name: fastapi_module_register
Version: 0.0.5
Summary: 通过将fastapi的模型自动注册路由
Project-URL: Homepage, https://github.com/dcshoecousa
Author-email: stan <gd19920125@hotmail.com>
License: MIT License
License-File: LICENSE
Classifier: License :: OSI Approved :: MIT License
Classifier: Operating System :: OS Independent
Classifier: Programming Language :: Python :: 3
Requires-Python: >=3.8
Requires-Dist: fastapi-pagination==0.12.4
Requires-Dist: fastapi>=0.95.1
Requires-Dist: sqlmodel==0.0.8
Requires-Dist: tortoise-orm>=0.19.3
Requires-Dist: ujson>=5.7.0
